pydantic_partial/__init__.py
pydantic_partial/partial.py
pydantic_partial/py.typed
pydantic_partial/utils.py
pydantic_partial-0.10.1.dist-info/licenses/LICENSE
pydantic_partial-0.10.1.dist-info/WHEEL
pydantic_partial-0.10.1.dist-info/METADATA
pydantic_partial-0.10.1.dist-info/RECORD
