Metadata-Version: 2.4
Name: pydantic-partial
Version: 0.10.1
Summary: Create partial models from your pydantic models. Partial models may allow None for certain or all fields.
Author: TEAM23 GmbH
Author-email: TEAM23 GmbH <info@team23.de>
License-Expression: MIT
License-File: LICENSE
Requires-Dist: pydantic>=2.0.0,<3.0.0
Requires-Python: >=3.10
Project-URL: Repository, https://github.com/team23/pydantic-partial
